{"interact_stonecutter":{"value":4},"eat_soup":{"value":0},"craft_tnt":{"value":0},"craft_spyglass":{"value":0},"interact_blast_furnace":{"value":16},"place_stairs":{"value":900},"drink_milk":{"value":0},"kill_phantom":{"value":1},"craft_compass":{"value":0},"kill_witch":{"value":1},"break_tools":{"value":85},"jump":{"value":70458},"use_bow":{"value":134},"mine_ice":{"value":1},"mine_grass":{"value":321},"mine_wood":{"value":1192},"eat_meat":{"value":449},"place_wall":{"value":3},"use_dirt":{"value":484},"interact_grindstone":{"value":142},"kill_hoglins":{"value":770},"mine_ancient_debris":{"value":18},"kill_polar_bear":{"value":0},"kill_ravager":{"value":0},"mine_lapis_ore":{"value":33},"interact_anvil":{"value":83},"craft_bookshelf":{"value":26},"kill_camel":{"value":0},"kill_blaze":{"value":0},"kill_parrot":{"value":0},"kill_chicken":{"value":54},"kill_snow_golem":{"value":0},"use_fireworks":{"value":0},"kill_bat":{"value":0},"interact_lectern":{"value":12},"kill_wolf":{"value":0},"ride_horse":{"value":198437},"use_potion":{"value":2},"sleep":{"value":29},"place_torch":{"value":1178},"craft_beacon":{"value":0},"harvest_nether_wart":{"value":0},"kill_fish":{"value":0},"open_container":{"value":4396},"kill_skeleton":{"value":24},"kill_zombified_piglin":{"value":63},"walk_on_water":{"value":322054},"ring_bell":{"value":17},"kill_piglin":{"value":34},"place_cactus":{"value":0},"eat_rawmeat":{"value":10},"mine_amethyst":{"value":0},"mine_glass":{"value":44},"collect_berries":{"value":50},"enchant":{"value":14},"craft_bundle":{"value":0},"craft_respawn_anchor":{"value":0},"craft_glowstone":{"value":0},"kill_any":{"value":1189},"use_egg":{"value":305},"sprint":{"value":7864397},"mine_iron_ore":{"value":277},"eat_veggie":{"value":110},"use_ender_pearl":{"value":2},"eat_cookie":{"value":0},"craft_mineral_block":{"value":608},"use_lava_bucket":{"value":0},"ride_strider":{"value":0},"kill_endermite":{"value":0},"kill_squid":{"value":6},"mine_ground":{"value":3726},"use_crossbow":{"value":0},"use_flint":{"value":3},"kill_iron_golem":{"value":0},"time_since_death":{"value":605639},"kill_turtle":{"value":0},"craft_armor":{"value":112},"kill_silverfish":{"value":0},"kill_wandering_trader":{"value":0},"harvest_bamboo":{"value":374},"eat_fish":{"value":283},"kill_ocelot":{"value":0},"use_hoe":{"value":157},"mine_nether_foliage":{"value":15},"killed_by_creeper":{"value":1},"place_conveyor":{"value":0},"kill_vex":{"value":0},"swim":{"value":565944},"kill_sheep":{"value":53},"drop":{"value":2696},"interact_cartography":{"value":4},"kill_ender_dragon":{"value":0},"mine_pointed_dripstone":{"value":14},"craft_bread":{"value":4},"crouch":{"value":650655},"place_lodestone":{"value":0},"use_shears":{"value":245},"ride_pig":{"value":26},"mine_spawner":{"value":0},"craft_sword":{"value":8},"mine_snow":{"value":145},"kill_pig":{"value":15},"kill_cow":{"value":61},"kill_panda":{"value":0},"mine_cobweb":{"value":5},"killed_by_warden":{"value":0},"place_bars":{"value":28},"biomes":{"value":17},"kill_tadpole":{"value":0},"mine_copper_ore":{"value":54},"interact_loom":{"value":40},"mine_stone":{"value":22228},"place_lightning_rod":{"value":4},"breed":{"value":667},"kill_illagers":{"value":0},"mine_diamond_ore":{"value":13},"pot_flower":{"value":3},"play":{"value":6595295},"place_electrics":{"value":98},"eat_junkfood":{"value":1},"aviate":{"value":0},"kill_rabbit":{"value":0},"kill_dolphin":{"value":0},"craft_recovery_compass":{"value":0},"climb":{"value":360161},"kill_guardian":{"value":0},"kill_piglin_brute":{"value":0},"kill_slime":{"value":0},"use_ender_eye":{"value":0},"craft_wool":{"value":171},"kill_villager":{"value":0},"kill_frog":{"value":0},"craft_tools":{"value":184},"kill_llama":{"value":0},"win_raid":{"value":0},"mine_nether_quartz_ore":{"value":770},"kill_ghast":{"value":2},"craft_paper":{"value":246},"use_snowball":{"value":0},"craft_ender_chest":{"value":0},"kill_magma_cube":{"value":11},"kill_creeper":{"value":9},"place_piston":{"value":6},"kill_horse":{"value":1},"fall":{"value":1227698},"place_chorus_flower":{"value":0},"mine_gold_ore":{"value":42},"kill_sniffer":{"value":0},"craft_sponge":{"value":0},"mine_coal_ore":{"value":331},"collect_shroom":{"value":11},"kill_spider":{"value":13},"place_candle":{"value":55},"interact_brewing_stand":{"value":8},"place_lantern":{"value":16},"place_scaffolding":{"value":441},"mine_obsidian":{"value":34},"kill_warden":{"value":0},"damage_shield":{"value":5379},"kill_goat":{"value":0},"place_sapling":{"value":111},"noteblock":{"value":1228},"kill_strider":{"value":0},"interact_campfire":{"value":0},"kill_fox":{"value":0},"place_glass":{"value":404},"place_rails":{"value":20},"use_goat_horn":{"value":0},"play_record":{"value":6},"ride_boat":{"value":2052568},"mine_redstone_ore":{"value":181},"mine_emerald_ore":{"value":3},"use_water_bucket":{"value":263},"kill_zombie":{"value":40},"use_honey_bottle":{"value":2},"damage_taken":{"value":56312},"kill_shulker":{"value":0},"kill_wither_skeleton":{"value":0},"kill_mooshroom":{"value":0},"use_book":{"value":10},"kill_axolotl":{"value":0},"harvest_sugar":{"value":265},"mine_dimensional":{"value":16222},"interact_smoker":{"value":595},"damage_dealt":{"value":326398},"death":{"value":28},"craft_clock":{"value":0},"place_sign":{"value":10},"trigger_raid":{"value":0},"time_since_sleep":{"value":150448},"kill_bee":{"value":0},"dive":{"value":403393},"craft_turtle_helmet":{"value":0},"place_banner":{"value":18},"ride_minecart":{"value":0},"kill_allay":{"value":0},"trade":{"value":0},"mine_coral":{"value":60},"mine_kelp":{"value":251},"kill_enderman":{"value":1},"walk":{"value":11425842},"use_totem":{"value":0}}