{"interact_stonecutter":{"rank":6,"value":188},"eat_soup":{"rank":4,"value":20},"craft_tnt":{"rank":14,"value":2},"craft_spyglass":{"rank":6,"value":1},"interact_blast_furnace":{"rank":33,"value":1},"place_stairs":{"rank":16,"value":3000},"drink_milk":{"value":0},"kill_phantom":{"rank":8,"value":270},"craft_compass":{"rank":10,"value":2},"kill_witch":{"rank":11,"value":8},"break_tools":{"rank":13,"value":121},"jump":{"rank":14,"value":209817},"use_bow":{"rank":9,"value":2657},"mine_ice":{"rank":15,"value":77},"mine_grass":{"rank":10,"value":1366},"mine_wood":{"rank":6,"value":4389},"eat_meat":{"rank":10,"value":864},"place_wall":{"rank":13,"value":370},"use_dirt":{"rank":17,"value":7565},"interact_grindstone":{"rank":14,"value":30},"kill_hoglins":{"rank":2,"value":42},"mine_ancient_debris":{"value":0},"kill_polar_bear":{"value":0},"kill_ravager":{"value":0},"mine_lapis_ore":{"rank":10,"value":55},"interact_anvil":{"rank":18,"value":74},"craft_bookshelf":{"rank":11,"value":55},"kill_camel":{"value":0},"kill_blaze":{"rank":10,"value":6},"kill_parrot":{"rank":2,"value":2},"kill_chicken":{"rank":24,"value":13},"kill_snow_golem":{"value":0},"use_fireworks":{"rank":24,"value":58},"kill_bat":{"value":0},"interact_lectern":{"rank":6,"value":108},"kill_wolf":{"rank":12,"value":3},"ride_horse":{"rank":2,"value":105456008},"use_potion":{"rank":7,"value":140},"sleep":{"rank":16,"value":170},"place_torch":{"rank":8,"value":2672},"craft_beacon":{"value":0},"harvest_nether_wart":{"value":0},"kill_fish":{"value":0},"open_container":{"rank":19,"value":8495},"kill_skeleton":{"rank":15,"value":297},"kill_zombified_piglin":{"rank":3,"value":322},"walk_on_water":{"rank":12,"value":1867482},"ring_bell":{"rank":7,"value":13},"kill_piglin":{"rank":5,"value":91},"place_cactus":{"rank":1,"value":220},"eat_rawmeat":{"rank":29,"value":6},"mine_amethyst":{"value":0},"mine_glass":{"rank":31,"value":8},"collect_berries":{"rank":11,"value":1179},"enchant":{"rank":18,"value":27},"craft_bundle":{"value":0},"craft_respawn_anchor":{"value":0},"craft_glowstone":{"rank":10,"value":22},"kill_any":{"rank":10,"value":3404},"use_egg":{"rank":27,"value":53},"sprint":{"rank":9,"value":45475056},"mine_iron_ore":{"rank":9,"value":674},"eat_veggie":{"rank":6,"value":3184},"use_ender_pearl":{"rank":15,"value":11},"eat_cookie":{"value":0},"craft_mineral_block":{"rank":7,"value":1942},"use_lava_bucket":{"rank":16,"value":23},"ride_strider":{"value":0},"kill_endermite":{"value":0},"kill_squid":{"value":0},"mine_ground":{"rank":19,"value":10743},"use_crossbow":{"rank":12,"value":3},"use_flint":{"rank":4,"value":1466},"kill_iron_golem":{"value":0},"time_since_death":{"rank":2,"value":8510261},"kill_turtle":{"value":0},"craft_armor":{"rank":12,"value":57},"kill_silverfish":{"value":0},"kill_wandering_trader":{"value":0},"harvest_bamboo":{"rank":7,"value":2002},"eat_fish":{"rank":23,"value":74},"kill_ocelot":{"value":0},"use_hoe":{"rank":9,"value":7699},"mine_nether_foliage":{"rank":6,"value":28},"killed_by_creeper":{"rank":14,"value":10},"place_conveyor":{"rank":11,"value":16},"kill_vex":{"value":0},"swim":{"rank":19,"value":1581897},"kill_sheep":{"rank":5,"value":237},"drop":{"rank":12,"value":3566},"interact_cartography":{"rank":10,"value":6},"kill_ender_dragon":{"rank":6,"value":1},"mine_pointed_dripstone":{"rank":9,"value":23},"craft_bread":{"rank":11,"value":389},"crouch":{"rank":16,"value":3172610},"place_lodestone":{"value":0},"use_shears":{"rank":11,"value":1683},"ride_pig":{"value":0},"mine_spawner":{"value":0},"craft_sword":{"rank":15,"value":11},"mine_snow":{"rank":22,"value":3},"kill_pig":{"rank":28,"value":6},"kill_cow":{"rank":9,"value":192},"kill_panda":{"value":0},"mine_cobweb":{"value":0},"killed_by_warden":{"value":0},"place_bars":{"rank":22,"value":22},"biomes":{"rank":17,"value":25},"kill_tadpole":{"value":0},"mine_copper_ore":{"rank":12,"value":63},"interact_loom":{"rank":7,"value":48},"mine_stone":{"rank":12,"value":29077},"place_lightning_rod":{"value":0},"breed":{"rank":8,"value":649},"kill_illagers":{"rank":11,"value":16},"mine_diamond_ore":{"rank":8,"value":60},"pot_flower":{"value":0},"play":{"rank":10,"value":23376036},"place_electrics":{"rank":23,"value":42},"eat_junkfood":{"rank":2,"value":96},"aviate":{"rank":22,"value":7361793},"kill_rabbit":{"value":0},"kill_dolphin":{"value":0},"craft_recovery_compass":{"value":0},"climb":{"rank":13,"value":845789},"kill_guardian":{"value":0},"kill_piglin_brute":{"value":0},"kill_slime":{"rank":17,"value":52},"use_ender_eye":{"value":0},"craft_wool":{"rank":12,"value":446},"kill_villager":{"value":0},"kill_frog":{"rank":7,"value":1},"craft_tools":{"rank":19,"value":133},"kill_llama":{"value":0},"win_raid":{"value":0},"mine_nether_quartz_ore":{"rank":5,"value":3782},"kill_ghast":{"rank":2,"value":35},"craft_paper":{"rank":18,"value":327},"use_snowball":{"rank":1,"value":284},"craft_ender_chest":{"value":0},"kill_magma_cube":{"rank":13,"value":34},"kill_creeper":{"rank":12,"value":191},"place_piston":{"value":0},"kill_horse":{"rank":27,"value":1},"fall":{"rank":13,"value":4676605},"place_chorus_flower":{"value":0},"mine_gold_ore":{"rank":9,"value":74},"kill_sniffer":{"value":0},"craft_sponge":{"value":0},"mine_coal_ore":{"rank":10,"value":726},"collect_shroom":{"rank":15,"value":318},"kill_spider":{"rank":15,"value":206},"place_candle":{"rank":22,"value":1},"interact_brewing_stand":{"rank":1,"value":726},"place_lantern":{"rank":12,"value":89},"place_scaffolding":{"rank":16,"value":588},"mine_obsidian":{"rank":13,"value":52},"kill_warden":{"value":0},"damage_shield":{"rank":14,"value":24261},"kill_goat":{"value":0},"place_sapling":{"rank":8,"value":292},"noteblock":{"rank":10,"value":51},"kill_strider":{"value":0},"interact_campfire":{"rank":12,"value":1},"kill_fox":{"value":0},"place_glass":{"rank":11,"value":1756},"place_rails":{"rank":6,"value":522},"use_goat_horn":{"rank":2,"value":404},"play_record":{"rank":6,"value":40},"ride_boat":{"rank":1,"value":76523303},"mine_redstone_ore":{"rank":7,"value":328},"mine_emerald_ore":{"rank":22,"value":5},"use_water_bucket":{"rank":13,"value":1134},"kill_zombie":{"rank":12,"value":980},"use_honey_bottle":{"value":0},"damage_taken":{"rank":18,"value":87021},"kill_shulker":{"value":0},"kill_wither_skeleton":{"rank":9,"value":11},"kill_mooshroom":{"value":0},"use_book":{"rank":3,"value":399},"kill_axolotl":{"value":0},"harvest_sugar":{"rank":11,"value":1316},"mine_dimensional":{"rank":11,"value":9041},"interact_smoker":{"rank":48,"value":1},"damage_dealt":{"rank":12,"value":315240},"death":{"rank":23,"value":35},"craft_clock":{"rank":2,"value":2},"place_sign":{"rank":15,"value":91},"trigger_raid":{"value":0},"time_since_sleep":{"rank":65,"value":4913},"kill_bee":{"value":0},"dive":{"rank":15,"value":1405751},"craft_turtle_helmet":{"value":0},"place_banner":{"rank":2,"value":358},"ride_minecart":{"rank":4,"value":3455625},"kill_allay":{"value":0},"trade":{"value":0},"mine_coral":{"rank":34,"value":1},"mine_kelp":{"rank":11,"value":766},"kill_enderman":{"rank":27,"value":3},"walk":{"rank":7,"value":57997481},"use_totem":{"value":0}}